MANIFEST.in
README.rst
setup.py
mtl/__init__.py
mtl/mtl.py
mtl.egg-info/PKG-INFO
mtl.egg-info/SOURCES.txt
mtl.egg-info/dependency_links.txt
mtl.egg-info/entry_points.txt
mtl.egg-info/requires.txt
mtl.egg-info/top_level.txt