Metadata-Version: 1.0
Name: mtl
Version: 0.0.1
Summary: moving time lapse
Home-page: https://github.com/jinyung/mtl
Author: Wong Jin Yung
Author-email: wongjinyung@gmail.com
License: MIT
Keywords: time-lapse barnacle
Platform: UNKNOWN
